README.md
setup.cfg
setup.py
idioms/__init__.py
idioms/__version__.py
idioms.egg-info/PKG-INFO
idioms.egg-info/SOURCES.txt
idioms.egg-info/dependency_links.txt
idioms.egg-info/requires.txt
idioms.egg-info/top_level.txt
idioms/models/AsyncSubprocess.py
idioms/models/AsyncSubprocessCallback.py
idioms/models/MatlabSimulation.py
idioms/models/SoundFx.py
idioms/models/__init__.py
idioms/utils/__init__.py
idioms/utils/pathutils.py
idioms/utils/soundutils.py
idioms/utils/stringutils.py